README.rst
setup.py
django_krate.egg-info/PKG-INFO
django_krate.egg-info/SOURCES.txt
django_krate.egg-info/dependency_links.txt
django_krate.egg-info/requires.txt
django_krate.egg-info/top_level.txt
krate/__init__.py
krate/core.py
krate/forms.py
krate/models.py
krate/settings.py
krate/ratehandlers/__init__.py
krate/ratehandlers/noratehandler.py
krate/ratehandlers/ratehandlerbase.py
krate/ratehandlers/dbratehandler/__init__.py
krate/ratehandlers/dbratehandler/models.py
krate/templatetags/__init__.py
krate/templatetags/krate.py
testing/__init__.py
testing/models.py
testing/settings.py
testing/urls.py
testing/tests/__init__.py
testing/tests/test_ratehandlers.py
testing/tests/test_templatetags.py